{
    "totalResults": 50,
    "startIndex": 1,
    "itemsPerPage": 25,
    "schemas": [
        "urn:ietf:params:scim:api:messages:2.0:ListResponse"
    ],
    "Resources": [
        {
            "emails": [
                {
                    "type": "work",
                    "primary": true
                }
            ],
            "displayName": "2192",
            "meta": {
                "created": "2023-03-08T14:57:16.634-06:00",
                "location": "http://10.0.0.33:3000/Users/0a0000fa86c310618186c303925a02fb",
                "lastModified": "2023-03-08T14:57:16.635-06:00",
                "version": "W/\"1678309036635\"",
                "resourceType": "User"
            },
            "schemas": [
                "urn:ietf:params:scim:schemas:core:2.0:User",
                "urn:ietf:params:scim:schemas:extension:enterprise:2.0:User",
                "urn:ietf:params:scim:schemas:extension:peppl:2.0:User"
            ],
            "name": {
                "formatted": "2192",
                "familyName": "Jensen",
                "givenName": "Barbara",
                "middleName": "Jane",
                "honorificPrefix": "Ms.",
                "honorificSuffix": "III"
            },
            "active": true,
            "id": "0a0000fa86c310618186c303925a02fb",
            "userName": "2192",
            "urn:ietf:params:scim:schemas:extension:enterprise:2.0:User": {
                "manager": {}
            },
            "urn:ietf:params:scim:schemas:extension:mainframe:2.0:User": {
                "entitlementOne": "full",
                "entitlementTwo": "none"
            },
            "urn:ietf:params:scim:schemas:extension:peppl:2.0:User": {
                "databaseAuthorizationId":"dbauth001",
                "transactionAuthorizationId":"trxauth001",
                "securityAdministratorIndicator": false,
                "dualVerificationIndicator": false,
                "inclusiveTransCode": false,
                "exclusiveTransCode": true    
            }
        },
        {
            "urn:ietf:params:scim:schemas:sailpoint:1.0:User": {
                "administrator": {},
                "capabilities": [],
                "costCenter": [],
                "isManager": false,
                "accounts": []
            },
            "emails": [
                {
                    "type": "work",
                    "primary": true
                }
            ],
            "displayName": "2971",
            "meta": {
                "created": "2023-03-08T14:57:17.052-06:00",
                "location": "http://10.0.0.33:3000/Users/0a0000fa86c310618186c30393fc030b",
                "lastModified": "2023-03-08T14:57:17.052-06:00",
                "version": "W/\"1678309037052\"",
                "resourceType": "User"
            },
            "schemas": [
                "urn:ietf:params:scim:schemas:sailpoint:1.0:User",
                "urn:ietf:params:scim:schemas:core:2.0:User",
                "urn:ietf:params:scim:schemas:extension:enterprise:2.0:User"
            ],
            "name": {
                "formatted": "2971"
            },
            "active": true,
            "id": "0a0000fa86c310618186c30393fc030b",
            "userName": "2971",
            "urn:ietf:params:scim:schemas:extension:enterprise:2.0:User": {
                "manager": {}
            }
        },
        {
            "urn:ietf:params:scim:schemas:sailpoint:1.0:User": {
                "administrator": {},
                "capabilities": [],
                "costCenter": [],
                "isManager": false,
                "accounts": []
            },
            "emails": [
                {
                    "type": "work",
                    "primary": true
                }
            ],
            "displayName": "10517",
            "meta": {
                "created": "2023-03-08T14:57:17.184-06:00",
                "location": "http://10.0.0.33:3000/Users/0a0000fa86c310618186c30394800311",
                "lastModified": "2023-03-08T14:57:17.185-06:00",
                "version": "W/\"1678309037185\"",
                "resourceType": "User"
            },
            "schemas": [
                "urn:ietf:params:scim:schemas:sailpoint:1.0:User",
                "urn:ietf:params:scim:schemas:core:2.0:User",
                "urn:ietf:params:scim:schemas:extension:enterprise:2.0:User"
            ],
            "name": {
                "formatted": "10517"
            },
            "active": true,
            "id": "0a0000fa86c310618186c30394800311",
            "userName": "10517",
            "urn:ietf:params:scim:schemas:extension:enterprise:2.0:User": {
                "manager": {}
            }
        },
        {
            "urn:ietf:params:scim:schemas:sailpoint:1.0:User": {
                "administrator": {},
                "capabilities": [],
                "costCenter": [],
                "isManager": false,
                "accounts": []
            },
            "emails": [
                {
                    "type": "work",
                    "primary": true
                }
            ],
            "displayName": "2188",
            "meta": {
                "created": "2023-03-08T14:57:17.717-06:00",
                "location": "http://10.0.0.33:3000/Users/0a0000fa86c310618186c30396950321",
                "lastModified": "2023-03-08T14:57:17.718-06:00",
                "version": "W/\"1678309037718\"",
                "resourceType": "User"
            },
            "schemas": [
                "urn:ietf:params:scim:schemas:sailpoint:1.0:User",
                "urn:ietf:params:scim:schemas:core:2.0:User",
                "urn:ietf:params:scim:schemas:extension:enterprise:2.0:User"
            ],
            "name": {
                "formatted": "2188"
            },
            "active": true,
            "id": "0a0000fa86c310618186c30396950321",
            "userName": "2188",
            "urn:ietf:params:scim:schemas:extension:enterprise:2.0:User": {
                "manager": {}
            }
        },
        {
            "urn:ietf:params:scim:schemas:sailpoint:1.0:User": {
                "administrator": {},
                "capabilities": [],
                "costCenter": [],
                "isManager": false,
                "accounts": []
            },
            "emails": [
                {
                    "type": "work",
                    "primary": true
                }
            ],
            "displayName": "2831",
            "meta": {
                "created": "2023-03-08T14:57:18.845-06:00",
                "location": "http://10.0.0.33:3000/Users/0a0000fa86c310618186c3039afd032c",
                "lastModified": "2023-03-08T14:57:18.846-06:00",
                "version": "W/\"1678309038846\"",
                "resourceType": "User"
            },
            "schemas": [
                "urn:ietf:params:scim:schemas:sailpoint:1.0:User",
                "urn:ietf:params:scim:schemas:core:2.0:User",
                "urn:ietf:params:scim:schemas:extension:enterprise:2.0:User"
            ],
            "name": {
                "formatted": "2831"
            },
            "active": true,
            "id": "0a0000fa86c310618186c3039afd032c",
            "userName": "2831",
            "urn:ietf:params:scim:schemas:extension:enterprise:2.0:User": {
                "manager": {}
            }
        },
        {
            "urn:ietf:params:scim:schemas:sailpoint:1.0:User": {
                "administrator": {},
                "capabilities": [],
                "costCenter": [],
                "isManager": false,
                "accounts": []
            },
            "emails": [
                {
                    "type": "work",
                    "primary": true
                }
            ],
            "displayName": "2105",
            "meta": {
                "created": "2023-03-08T14:57:23.118-06:00",
                "location": "http://10.0.0.33:3000/Users/0a0000fa86c310618186c303abae0378",
                "lastModified": "2023-03-08T14:57:23.119-06:00",
                "version": "W/\"1678309043119\"",
                "resourceType": "User"
            },
            "schemas": [
                "urn:ietf:params:scim:schemas:sailpoint:1.0:User",
                "urn:ietf:params:scim:schemas:core:2.0:User",
                "urn:ietf:params:scim:schemas:extension:enterprise:2.0:User"
            ],
            "name": {
                "formatted": "2105"
            },
            "active": true,
            "id": "0a0000fa86c310618186c303abae0378",
            "userName": "2105",
            "urn:ietf:params:scim:schemas:extension:enterprise:2.0:User": {
                "manager": {}
            }
        },
        {
            "urn:ietf:params:scim:schemas:sailpoint:1.0:User": {
                "administrator": {},
                "capabilities": [],
                "costCenter": [],
                "isManager": false,
                "accounts": []
            },
            "emails": [
                {
                    "type": "work",
                    "primary": true
                }
            ],
            "displayName": "1738",
            "meta": {
                "created": "2023-03-08T14:57:23.255-06:00",
                "location": "http://10.0.0.33:3000/Users/0a0000fa86c310618186c303ac36037e",
                "lastModified": "2023-03-08T14:57:23.256-06:00",
                "version": "W/\"1678309043256\"",
                "resourceType": "User"
            },
            "schemas": [
                "urn:ietf:params:scim:schemas:sailpoint:1.0:User",
                "urn:ietf:params:scim:schemas:core:2.0:User",
                "urn:ietf:params:scim:schemas:extension:enterprise:2.0:User"
            ],
            "name": {
                "formatted": "1738"
            },
            "active": true,
            "id": "0a0000fa86c310618186c303ac36037e",
            "userName": "1738",
            "urn:ietf:params:scim:schemas:extension:enterprise:2.0:User": {
                "manager": {}
            }
        },
        {
            "urn:ietf:params:scim:schemas:sailpoint:1.0:User": {
                "administrator": {},
                "capabilities": [],
                "costCenter": [],
                "isManager": false,
                "accounts": []
            },
            "emails": [
                {
                    "type": "work",
                    "primary": true
                }
            ],
            "displayName": "2873",
            "meta": {
                "created": "2023-03-08T14:57:23.364-06:00",
                "location": "http://10.0.0.33:3000/Users/0a0000fa86c310618186c303aca40384",
                "lastModified": "2023-03-08T14:57:23.365-06:00",
                "version": "W/\"1678309043365\"",
                "resourceType": "User"
            },
            "schemas": [
                "urn:ietf:params:scim:schemas:sailpoint:1.0:User",
                "urn:ietf:params:scim:schemas:core:2.0:User",
                "urn:ietf:params:scim:schemas:extension:enterprise:2.0:User"
            ],
            "name": {
                "formatted": "2873"
            },
            "active": true,
            "id": "0a0000fa86c310618186c303aca40384",
            "userName": "2873",
            "urn:ietf:params:scim:schemas:extension:enterprise:2.0:User": {
                "manager": {}
            }
        },
        {
            "urn:ietf:params:scim:schemas:sailpoint:1.0:User": {
                "administrator": {},
                "capabilities": [],
                "costCenter": [],
                "isManager": false,
                "accounts": []
            },
            "emails": [
                {
                    "type": "work",
                    "primary": true
                }
            ],
            "displayName": "3026",
            "meta": {
                "created": "2023-03-08T14:57:23.542-06:00",
                "location": "http://10.0.0.33:3000/Users/0a0000fa86c310618186c303ad56038f",
                "lastModified": "2023-03-08T14:57:23.542-06:00",
                "version": "W/\"1678309043542\"",
                "resourceType": "User"
            },
            "schemas": [
                "urn:ietf:params:scim:schemas:sailpoint:1.0:User",
                "urn:ietf:params:scim:schemas:core:2.0:User",
                "urn:ietf:params:scim:schemas:extension:enterprise:2.0:User"
            ],
            "name": {
                "formatted": "3026"
            },
            "active": true,
            "id": "0a0000fa86c310618186c303ad56038f",
            "userName": "3026",
            "urn:ietf:params:scim:schemas:extension:enterprise:2.0:User": {
                "manager": {}
            }
        },
        {
            "urn:ietf:params:scim:schemas:sailpoint:1.0:User": {
                "administrator": {},
                "capabilities": [],
                "costCenter": [],
                "isManager": false,
                "accounts": []
            },
            "emails": [
                {
                    "type": "work",
                    "primary": true
                }
            ],
            "displayName": "10198",
            "meta": {
                "created": "2023-03-08T14:57:23.657-06:00",
                "location": "http://10.0.0.33:3000/Users/0a0000fa86c310618186c303adc90395",
                "lastModified": "2023-03-08T14:57:23.658-06:00",
                "version": "W/\"1678309043658\"",
                "resourceType": "User"
            },
            "schemas": [
                "urn:ietf:params:scim:schemas:sailpoint:1.0:User",
                "urn:ietf:params:scim:schemas:core:2.0:User",
                "urn:ietf:params:scim:schemas:extension:enterprise:2.0:User"
            ],
            "name": {
                "formatted": "10198"
            },
            "active": true,
            "id": "0a0000fa86c310618186c303adc90395",
            "userName": "10198",
            "urn:ietf:params:scim:schemas:extension:enterprise:2.0:User": {
                "manager": {}
            }
        },
        {
            "urn:ietf:params:scim:schemas:sailpoint:1.0:User": {
                "administrator": {},
                "capabilities": [],
                "costCenter": [],
                "isManager": false,
                "accounts": []
            },
            "emails": [
                {
                    "type": "work",
                    "primary": true
                }
            ],
            "displayName": "1807",
            "meta": {
                "created": "2023-03-08T14:57:23.766-06:00",
                "location": "http://10.0.0.33:3000/Users/0a0000fa86c310618186c303ae35039b",
                "lastModified": "2023-03-08T14:57:23.766-06:00",
                "version": "W/\"1678309043766\"",
                "resourceType": "User"
            },
            "schemas": [
                "urn:ietf:params:scim:schemas:sailpoint:1.0:User",
                "urn:ietf:params:scim:schemas:core:2.0:User",
                "urn:ietf:params:scim:schemas:extension:enterprise:2.0:User"
            ],
            "name": {
                "formatted": "1807"
            },
            "active": true,
            "id": "0a0000fa86c310618186c303ae35039b",
            "userName": "1807",
            "urn:ietf:params:scim:schemas:extension:enterprise:2.0:User": {
                "manager": {}
            }
        },
        {
            "urn:ietf:params:scim:schemas:sailpoint:1.0:User": {
                "administrator": {},
                "capabilities": [],
                "costCenter": [],
                "isManager": false,
                "accounts": []
            },
            "emails": [
                {
                    "type": "work",
                    "primary": true
                }
            ],
            "displayName": "2257",
            "meta": {
                "created": "2023-03-08T14:57:23.853-06:00",
                "location": "http://10.0.0.33:3000/Users/0a0000fa86c310618186c303ae8d03a1",
                "lastModified": "2023-03-08T14:57:23.854-06:00",
                "version": "W/\"1678309043854\"",
                "resourceType": "User"
            },
            "schemas": [
                "urn:ietf:params:scim:schemas:sailpoint:1.0:User",
                "urn:ietf:params:scim:schemas:core:2.0:User",
                "urn:ietf:params:scim:schemas:extension:enterprise:2.0:User"
            ],
            "name": {
                "formatted": "2257"
            },
            "active": true,
            "id": "0a0000fa86c310618186c303ae8d03a1",
            "userName": "2257",
            "urn:ietf:params:scim:schemas:extension:enterprise:2.0:User": {
                "manager": {}
            }
        },
        {
            "urn:ietf:params:scim:schemas:sailpoint:1.0:User": {
                "administrator": {},
                "capabilities": [],
                "costCenter": [],
                "isManager": false,
                "accounts": []
            },
            "emails": [
                {
                    "type": "work",
                    "primary": true
                }
            ],
            "displayName": "2536",
            "meta": {
                "created": "2023-03-08T14:57:23.946-06:00",
                "location": "http://10.0.0.33:3000/Users/0a0000fa86c310618186c303aeea03a7",
                "lastModified": "2023-03-08T14:57:23.947-06:00",
                "version": "W/\"1678309043947\"",
                "resourceType": "User"
            },
            "schemas": [
                "urn:ietf:params:scim:schemas:sailpoint:1.0:User",
                "urn:ietf:params:scim:schemas:core:2.0:User",
                "urn:ietf:params:scim:schemas:extension:enterprise:2.0:User"
            ],
            "name": {
                "formatted": "2536"
            },
            "active": true,
            "id": "0a0000fa86c310618186c303aeea03a7",
            "userName": "2536",
            "urn:ietf:params:scim:schemas:extension:enterprise:2.0:User": {
                "manager": {}
            }
        },
        {
            "urn:ietf:params:scim:schemas:sailpoint:1.0:User": {
                "administrator": {},
                "capabilities": [],
                "costCenter": [],
                "isManager": false,
                "accounts": []
            },
            "emails": [
                {
                    "type": "work",
                    "primary": true
                }
            ],
            "displayName": "2289",
            "meta": {
                "created": "2023-03-08T14:57:24.095-06:00",
                "location": "http://10.0.0.33:3000/Users/0a0000fa86c310618186c303af7f03b2",
                "lastModified": "2023-03-08T14:57:24.096-06:00",
                "version": "W/\"1678309044096\"",
                "resourceType": "User"
            },
            "schemas": [
                "urn:ietf:params:scim:schemas:sailpoint:1.0:User",
                "urn:ietf:params:scim:schemas:core:2.0:User",
                "urn:ietf:params:scim:schemas:extension:enterprise:2.0:User"
            ],
            "name": {
                "formatted": "2289"
            },
            "active": true,
            "id": "0a0000fa86c310618186c303af7f03b2",
            "userName": "2289",
            "urn:ietf:params:scim:schemas:extension:enterprise:2.0:User": {
                "manager": {}
            }
        },
        {
            "urn:ietf:params:scim:schemas:sailpoint:1.0:User": {
                "administrator": {},
                "capabilities": [],
                "costCenter": [],
                "isManager": false,
                "accounts": []
            },
            "emails": [
                {
                    "type": "work",
                    "primary": true
                }
            ],
            "displayName": "1663",
            "meta": {
                "created": "2023-03-08T14:57:24.418-06:00",
                "location": "http://10.0.0.33:3000/Users/0a0000fa86c310618186c303b0c203c2",
                "lastModified": "2023-03-08T14:57:24.419-06:00",
                "version": "W/\"1678309044419\"",
                "resourceType": "User"
            },
            "schemas": [
                "urn:ietf:params:scim:schemas:sailpoint:1.0:User",
                "urn:ietf:params:scim:schemas:core:2.0:User",
                "urn:ietf:params:scim:schemas:extension:enterprise:2.0:User"
            ],
            "name": {
                "formatted": "1663"
            },
            "active": true,
            "id": "0a0000fa86c310618186c303b0c203c2",
            "userName": "1663",
            "urn:ietf:params:scim:schemas:extension:enterprise:2.0:User": {
                "manager": {}
            }
        },
        {
            "urn:ietf:params:scim:schemas:sailpoint:1.0:User": {
                "administrator": {},
                "capabilities": [],
                "costCenter": [],
                "isManager": false,
                "accounts": []
            },
            "emails": [
                {
                    "type": "work",
                    "primary": true
                }
            ],
            "displayName": "1972",
            "meta": {
                "created": "2023-03-08T14:57:24.518-06:00",
                "location": "http://10.0.0.33:3000/Users/0a0000fa86c310618186c303b12603c8",
                "lastModified": "2023-03-08T14:57:24.519-06:00",
                "version": "W/\"1678309044519\"",
                "resourceType": "User"
            },
            "schemas": [
                "urn:ietf:params:scim:schemas:sailpoint:1.0:User",
                "urn:ietf:params:scim:schemas:core:2.0:User",
                "urn:ietf:params:scim:schemas:extension:enterprise:2.0:User"
            ],
            "name": {
                "formatted": "1972"
            },
            "active": true,
            "id": "0a0000fa86c310618186c303b12603c8",
            "userName": "1972",
            "urn:ietf:params:scim:schemas:extension:enterprise:2.0:User": {
                "manager": {}
            }
        },
        {
            "urn:ietf:params:scim:schemas:sailpoint:1.0:User": {
                "administrator": {},
                "capabilities": [],
                "costCenter": [],
                "isManager": false,
                "accounts": []
            },
            "emails": [
                {
                    "type": "work",
                    "primary": true
                }
            ],
            "displayName": "2296",
            "meta": {
                "created": "2023-03-08T14:57:24.878-06:00",
                "location": "http://10.0.0.33:3000/Users/0a0000fa86c310618186c303b28e03dd",
                "lastModified": "2023-03-08T14:57:24.878-06:00",
                "version": "W/\"1678309044878\"",
                "resourceType": "User"
            },
            "schemas": [
                "urn:ietf:params:scim:schemas:sailpoint:1.0:User",
                "urn:ietf:params:scim:schemas:core:2.0:User",
                "urn:ietf:params:scim:schemas:extension:enterprise:2.0:User"
            ],
            "name": {
                "formatted": "2296"
            },
            "active": true,
            "id": "0a0000fa86c310618186c303b28e03dd",
            "userName": "2296",
            "urn:ietf:params:scim:schemas:extension:enterprise:2.0:User": {
                "manager": {}
            }
        },
        {
            "urn:ietf:params:scim:schemas:sailpoint:1.0:User": {
                "administrator": {},
                "capabilities": [],
                "costCenter": [],
                "isManager": false,
                "accounts": []
            },
            "emails": [
                {
                    "type": "work",
                    "primary": true
                }
            ],
            "displayName": "9812",
            "meta": {
                "created": "2023-03-08T14:57:25.057-06:00",
                "location": "http://10.0.0.33:3000/Users/0a0000fa86c310618186c303b34003e8",
                "lastModified": "2023-03-08T14:57:25.058-06:00",
                "version": "W/\"1678309045058\"",
                "resourceType": "User"
            },
            "schemas": [
                "urn:ietf:params:scim:schemas:sailpoint:1.0:User",
                "urn:ietf:params:scim:schemas:core:2.0:User",
                "urn:ietf:params:scim:schemas:extension:enterprise:2.0:User"
            ],
            "name": {
                "formatted": "9812"
            },
            "active": true,
            "id": "0a0000fa86c310618186c303b34003e8",
            "userName": "9812",
            "urn:ietf:params:scim:schemas:extension:enterprise:2.0:User": {
                "manager": {}
            }
        },
        {
            "urn:ietf:params:scim:schemas:sailpoint:1.0:User": {
                "administrator": {},
                "capabilities": [],
                "costCenter": [],
                "isManager": false,
                "accounts": []
            },
            "emails": [
                {
                    "type": "work",
                    "primary": true
                }
            ],
            "displayName": "3049",
            "meta": {
                "created": "2023-03-08T14:57:25.164-06:00",
                "location": "http://10.0.0.33:3000/Users/0a0000fa86c310618186c303b3ac03ee",
                "lastModified": "2023-03-08T14:57:25.165-06:00",
                "version": "W/\"1678309045165\"",
                "resourceType": "User"
            },
            "schemas": [
                "urn:ietf:params:scim:schemas:sailpoint:1.0:User",
                "urn:ietf:params:scim:schemas:core:2.0:User",
                "urn:ietf:params:scim:schemas:extension:enterprise:2.0:User"
            ],
            "name": {
                "formatted": "3049"
            },
            "active": true,
            "id": "0a0000fa86c310618186c303b3ac03ee",
            "userName": "3049",
            "urn:ietf:params:scim:schemas:extension:enterprise:2.0:User": {
                "manager": {}
            }
        },
        {
            "urn:ietf:params:scim:schemas:sailpoint:1.0:User": {
                "administrator": {},
                "capabilities": [],
                "costCenter": [],
                "isManager": false,
                "accounts": []
            },
            "emails": [
                {
                    "type": "work",
                    "primary": true
                }
            ],
            "displayName": "2433",
            "meta": {
                "created": "2023-03-08T14:57:25.334-06:00",
                "location": "http://10.0.0.33:3000/Users/0a0000fa86c310618186c303b45503f4",
                "lastModified": "2023-03-08T14:57:25.334-06:00",
                "version": "W/\"1678309045334\"",
                "resourceType": "User"
            },
            "schemas": [
                "urn:ietf:params:scim:schemas:sailpoint:1.0:User",
                "urn:ietf:params:scim:schemas:core:2.0:User",
                "urn:ietf:params:scim:schemas:extension:enterprise:2.0:User"
            ],
            "name": {
                "formatted": "2433"
            },
            "active": true,
            "id": "0a0000fa86c310618186c303b45503f4",
            "userName": "2433",
            "urn:ietf:params:scim:schemas:extension:enterprise:2.0:User": {
                "manager": {}
            }
        },
        {
            "urn:ietf:params:scim:schemas:sailpoint:1.0:User": {
                "administrator": {},
                "capabilities": [],
                "costCenter": [],
                "isManager": false,
                "accounts": []
            },
            "emails": [
                {
                    "type": "work",
                    "primary": true
                }
            ],
            "displayName": "10347",
            "meta": {
                "created": "2023-03-08T14:57:25.574-06:00",
                "location": "http://10.0.0.33:3000/Users/0a0000fa86c310618186c303b54603fa",
                "lastModified": "2023-03-08T14:57:25.575-06:00",
                "version": "W/\"1678309045575\"",
                "resourceType": "User"
            },
            "schemas": [
                "urn:ietf:params:scim:schemas:sailpoint:1.0:User",
                "urn:ietf:params:scim:schemas:core:2.0:User",
                "urn:ietf:params:scim:schemas:extension:enterprise:2.0:User"
            ],
            "name": {
                "formatted": "10347"
            },
            "active": true,
            "id": "0a0000fa86c310618186c303b54603fa",
            "userName": "10347",
            "urn:ietf:params:scim:schemas:extension:enterprise:2.0:User": {
                "manager": {}
            }
        },
        {
            "urn:ietf:params:scim:schemas:sailpoint:1.0:User": {
                "administrator": {},
                "capabilities": [],
                "costCenter": [],
                "isManager": false,
                "accounts": []
            },
            "emails": [
                {
                    "type": "work",
                    "primary": true
                }
            ],
            "displayName": "10901",
            "meta": {
                "created": "2023-03-08T14:57:26.643-06:00",
                "location": "http://10.0.0.33:3000/Users/0a0000fa86c310618186c303b9730437",
                "lastModified": "2023-03-08T14:57:26.644-06:00",
                "version": "W/\"1678309046644\"",
                "resourceType": "User"
            },
            "schemas": [
                "urn:ietf:params:scim:schemas:sailpoint:1.0:User",
                "urn:ietf:params:scim:schemas:core:2.0:User",
                "urn:ietf:params:scim:schemas:extension:enterprise:2.0:User"
            ],
            "name": {
                "formatted": "10901"
            },
            "active": true,
            "id": "0a0000fa86c310618186c303b9730437",
            "userName": "10901",
            "urn:ietf:params:scim:schemas:extension:enterprise:2.0:User": {
                "manager": {}
            }
        },
        {
            "urn:ietf:params:scim:schemas:sailpoint:1.0:User": {
                "administrator": {},
                "capabilities": [],
                "costCenter": [],
                "isManager": false,
                "accounts": []
            },
            "emails": [
                {
                    "type": "work",
                    "primary": true
                }
            ],
            "displayName": "2042",
            "meta": {
                "created": "2023-03-08T14:57:26.808-06:00",
                "location": "http://10.0.0.33:3000/Users/0a0000fa86c310618186c303ba180442",
                "lastModified": "2023-03-08T14:57:26.812-06:00",
                "version": "W/\"1678309046812\"",
                "resourceType": "User"
            },
            "schemas": [
                "urn:ietf:params:scim:schemas:sailpoint:1.0:User",
                "urn:ietf:params:scim:schemas:core:2.0:User",
                "urn:ietf:params:scim:schemas:extension:enterprise:2.0:User"
            ],
            "name": {
                "formatted": "2042"
            },
            "active": true,
            "id": "0a0000fa86c310618186c303ba180442",
            "userName": "2042",
            "urn:ietf:params:scim:schemas:extension:enterprise:2.0:User": {
                "manager": {}
            }
        },
        {
            "urn:ietf:params:scim:schemas:sailpoint:1.0:User": {
                "administrator": {},
                "capabilities": [],
                "costCenter": [],
                "isManager": false,
                "accounts": []
            },
            "emails": [
                {
                    "type": "work",
                    "primary": true
                }
            ],
            "displayName": "2162",
            "meta": {
                "created": "2023-03-08T14:57:27.124-06:00",
                "location": "http://10.0.0.33:3000/Users/0a0000fa86c310618186c303bb540457",
                "lastModified": "2023-03-08T14:57:27.125-06:00",
                "version": "W/\"1678309047125\"",
                "resourceType": "User"
            },
            "schemas": [
                "urn:ietf:params:scim:schemas:sailpoint:1.0:User",
                "urn:ietf:params:scim:schemas:core:2.0:User",
                "urn:ietf:params:scim:schemas:extension:enterprise:2.0:User"
            ],
            "name": {
                "formatted": "2162"
            },
            "active": true,
            "id": "0a0000fa86c310618186c303bb540457",
            "userName": "2162",
            "urn:ietf:params:scim:schemas:extension:enterprise:2.0:User": {
                "manager": {}
            }
        }
   ]
}